eeg_toolbox/__init__.py
eeg_toolbox/detection.py
eeg_toolbox/fourier_of_data.py
eeg_toolbox/load.py
eeg_toolbox/processing.py
eeg_toolbox/visual.py
eeg_toolbox-0.1.0.dist-info/METADATA
eeg_toolbox-0.1.0.dist-info/WHEEL
eeg_toolbox-0.1.0.dist-info/top_level.txt
eeg_toolbox-0.1.0.dist-info/RECORD
