Metadata-Version: 2.4
Name: eeg_toolbox
Version: 0.1.0
Summary: A simple EEG signal processing toolbox
Home-page: https://github.com/hubakukor/scipy_proj
Author: Veronika Szabolcsi, Dorka Kecskés, Huba Kukor
Classifier: Programming Language :: Python :: 3
Requires-Python: >=3.10
Requires-Dist: numpy
Requires-Dist: scipy
Requires-Dist: mne
Requires-Dist: matplotlib
Dynamic: author
Dynamic: classifier
Dynamic: description
Dynamic: description-content-type
Dynamic: home-page
Dynamic: requires-dist
Dynamic: requires-python
Dynamic: summary
